splints/rules.py
splints/server.py
splints/plugins/default.py
splints/types/linting.py
splints-0.0.3.dist-info/licenses/LICENSE
splints-0.0.3.dist-info/METADATA
splints-0.0.3.dist-info/WHEEL
splints-0.0.3.dist-info/entry_points.txt
splints-0.0.3.dist-info/top_level.txt
splints-0.0.3.dist-info/RECORD
