Metadata-Version: 2.4
Name: splints
Version: 0.0.3
License-File: LICENSE
Requires-Dist: pyyaml
Requires-Dist: pygls==1.3.1
Dynamic: license-file
